superparsenmap/__init__.py
superparsenmap/__main__.py
superparsenmap-1.2.1.dist-info/LICENSE
superparsenmap-1.2.1.dist-info/METADATA
superparsenmap-1.2.1.dist-info/WHEEL
superparsenmap-1.2.1.dist-info/entry_points.txt
superparsenmap-1.2.1.dist-info/top_level.txt
superparsenmap-1.2.1.dist-info/RECORD
