Metadata-Version: 2.1
Name: superparsenmap
Version: 1.2.1
Summary: SuperParseNmap is a command line utility that parses nmap XML into CSV or Excel format.
Author-email: Jonathan Farley <jonffarley@gmail.com>
License: GNU General Public License
Project-URL: Homepage, https://github.com/jfarl/superparsenmap
Keywords: nmap,parser,excel,csv
Classifier: Development Status :: 5 - Production/Stable
Classifier: License :: OSI Approved :: GNU General Public License v3 or later (GPLv3+)
Classifier: Intended Audience :: Information Technology
Classifier: Intended Audience :: System Administrators
Classifier: Intended Audience :: Telecommunications Industry
Classifier: Topic :: Security
Classifier: Programming Language :: Python :: 3.4
Classifier: Programming Language :: Python :: 3.5
Classifier: Programming Language :: Python :: 3.6
Classifier: Programming Language :: Python :: 3.7
Classifier: Programming Language :: Python :: 3.8
Classifier: Programming Language :: Python :: 3.9
Classifier: Programming Language :: Python :: 3.10
Classifier: Programming Language :: Python :: 3.11
Classifier: Operating System :: OS Independent
Requires-Python: >=3.4
License-File: LICENSE
Requires-Dist: pandas ==1.5.3
Requires-Dist: python-libnmap ==0.7.3
Requires-Dist: xlsxwriter ==3.1.2
Requires-Dist: argparse ==1.4.0
Requires-Dist: importlib-metadata ==6.8.0
